<?xml version="1.0" encoding="UTF-8"?>
<Document id="0001465" source="ADAM" url="https://www.nlm.nih.gov/medlineplus/ency/article/002584.htm">
 <!--Answers from the A.D.A.M. medical encyclopedia were removed to comply with the MedlinePlus copyright-->
<Focus>Estrogen overdose</Focus>
<FocusAnnotations>
	<Category>Disease</Category>
	<UMLS>
		<CUIs>
			<CUI>C0573767</CUI>
		</CUIs>
		<SemanticTypes>
			<SemanticType>T037</SemanticType>
		</SemanticTypes>
		<SemanticGroup>Disorders</SemanticGroup>
	</UMLS>
</FocusAnnotations>
<QAPairs>
	<QAPair pid="1">
			<Question qid="0001465-1" qtype="information">What is (are) Estrogen overdose ?</Question>
			<Answer></Answer>
	</QAPair>
	<QAPair pid="4">
			<Question qid="0001465-4" qtype="symptoms">What are the symptoms of Estrogen overdose ?</Question>
			<Answer></Answer>
	</QAPair>
	<QAPair pid="5">
			<Question qid="0001465-5" qtype="considerations">What to do for Estrogen overdose ?</Question>
			<Answer></Answer>
	</QAPair>
	<QAPair pid="8">
			<Question qid="0001465-8" qtype="outlook">What is the outlook for Estrogen overdose ?</Question>
			<Answer></Answer>
	</QAPair>
	<QAPair pid="9">
			<Question qid="0001465-9" qtype="outlook">What is the outlook for Estrogen overdose ?</Question>
			<Answer></Answer>
	</QAPair>
</QAPairs>
</Document>
