<?xml version="1.0" encoding="UTF-8"?>
<Document id="0001483" source="ADAM" url="https://www.nlm.nih.gov/medlineplus/ency/article/003878.htm">
 <!--Answers from the A.D.A.M. medical encyclopedia were removed to comply with the MedlinePlus copyright-->
<Focus>Exercise stress test</Focus>
<FocusAnnotations>
	<Category>Other</Category>
	<Synonyms>
		<Synonym>Exercise ECG</Synonym>
		<Synonym>ECG - exercise treadmill</Synonym>
		<Synonym>EKG - exercise treadmill</Synonym>
		<Synonym>Stress ECG</Synonym>
		<Synonym>Exercise electrocardiography</Synonym>
		<Synonym>Stress test - Exercise treadmill</Synonym>
		<Synonym>CAD - treadmill</Synonym>
		<Synonym>Coronary artery disease - treadmill</Synonym>
		<Synonym>Chest pain - treadmill</Synonym>
		<Synonym>Angina - treadmill</Synonym>
		<Synonym>Heart disease - treadmill</Synonym>
	</Synonyms>
</FocusAnnotations>
<QAPairs>
	<QAPair pid="1">
			<Question qid="0001483-1" qtype="information">Do you have information about Exercise stress test</Question>
			<Answer></Answer>
	</QAPair>
</QAPairs>
</Document>
