<?xml version="1.0" encoding="UTF-8"?>
<Document id="0002101" source="ADAM" url="https://www.nlm.nih.gov/medlineplus/ency/article/001461.htm">
 <!--Answers from the A.D.A.M. medical encyclopedia were removed to comply with the MedlinePlus copyright-->
<Focus>Hypomelanosis of Ito</Focus>
<FocusAnnotations>
	<Category>Disease</Category>
	<UMLS>
		<CUIs>
			<CUI>C0022283</CUI>
		</CUIs>
		<SemanticTypes>
			<SemanticType>T019</SemanticType>
			<SemanticType>T047</SemanticType>
		</SemanticTypes>
		<SemanticGroup>Disorders</SemanticGroup>
	</UMLS>
	<Synonyms>
		<Synonym>Incontinentia pigmenti achromians</Synonym>
	</Synonyms>
</FocusAnnotations>
<QAPairs>
	<QAPair pid="1">
			<Question qid="0002101-1" qtype="information">What is (are) Hypomelanosis of Ito ?</Question>
			<Answer></Answer>
	</QAPair>
	<QAPair pid="2">
			<Question qid="0002101-2" qtype="causes">What causes Hypomelanosis of Ito ?</Question>
			<Answer></Answer>
	</QAPair>
	<QAPair pid="3">
			<Question qid="0002101-3" qtype="symptoms">What are the symptoms of Hypomelanosis of Ito ?</Question>
			<Answer></Answer>
	</QAPair>
	<QAPair pid="4">
			<Question qid="0002101-4" qtype="exams and tests">How to diagnose Hypomelanosis of Ito ?</Question>
			<Answer></Answer>
	</QAPair>
	<QAPair pid="5">
			<Question qid="0002101-5" qtype="treatment">What are the treatments for Hypomelanosis of Ito ?</Question>
			<Answer></Answer>
	</QAPair>
	<QAPair pid="6">
			<Question qid="0002101-6" qtype="outlook">What is the outlook for Hypomelanosis of Ito ?</Question>
			<Answer></Answer>
	</QAPair>
	<QAPair pid="7">
			<Question qid="0002101-7" qtype="complications">What are the complications of Hypomelanosis of Ito ?</Question>
			<Answer></Answer>
	</QAPair>
	<QAPair pid="8">
			<Question qid="0002101-8" qtype="when to contact a medical professional">Do I need to see a doctor for Hypomelanosis of Ito ?</Question>
			<Answer></Answer>
	</QAPair>
</QAPairs>
</Document>
