<?xml version="1.0" encoding="UTF-8"?>
<Document id="0002346" source="ADAM" url="https://www.nlm.nih.gov/medlineplus/ency/patientinstructions/000499.htm">
 <!--Answers from the A.D.A.M. medical encyclopedia were removed to comply with the MedlinePlus copyright-->
<Focus>Latex allergies - for hospital patients</Focus>
<FocusAnnotations>
	<Category>Disease</Category>
	<UMLS>
		<CUIs>
			<CUI>C0239966</CUI>
			<CUI>C0577628</CUI>
		</CUIs>
		<SemanticTypes>
			<SemanticType>T046</SemanticType>
			<SemanticType>T033</SemanticType>
		</SemanticTypes>
		<SemanticGroup>Disorders</SemanticGroup>
	</UMLS>
</FocusAnnotations>
<QAPairs>
	<QAPair pid="1">
			<Question qid="0002346-1" qtype="information">What is (are) Latex allergies - for hospital patients ?</Question>
			<Answer></Answer>
	</QAPair>
	<QAPair pid="2">
			<Question qid="0002346-2" qtype="information">What is (are) Latex allergies - for hospital patients ?</Question>
			<Answer></Answer>
	</QAPair>
	<QAPair pid="4">
			<Question qid="0002346-4" qtype="susceptibility">Who is at risk for Latex allergies - for hospital patients? ?</Question>
			<Answer></Answer>
	</QAPair>
	<QAPair pid="5">
			<Question qid="0002346-5" qtype="exams and tests">How to diagnose Latex allergies - for hospital patients ?</Question>
			<Answer></Answer>
	</QAPair>
	<QAPair pid="6">
			<Question qid="0002346-6" qtype="symptoms">What are the symptoms of Latex allergies - for hospital patients ?</Question>
			<Answer></Answer>
	</QAPair>
</QAPairs>
</Document>
