<?xml version="1.0" encoding="UTF-8"?>
<Document id="0003449" source="ADAM" url="https://www.nlm.nih.gov/medlineplus/ency/patientinstructions/000610.htm">
 <!--Answers from the A.D.A.M. medical encyclopedia were removed to comply with the MedlinePlus copyright-->
<Focus>Sacroiliac joint pain - aftercare</Focus>
<FocusAnnotations>
	<Category>Disease</Category>
	<UMLS>
		<CUIs>
			<CUI>C0458232</CUI>
		</CUIs>
		<SemanticTypes>
			<SemanticType>T184</SemanticType>
		</SemanticTypes>
		<SemanticGroup>Disorders</SemanticGroup>
	</UMLS>
	<Synonyms>
		<Synonym>SIJ pain - aftercare</Synonym>
		<Synonym>SIJ dysfunction - aftercare</Synonym>
		<Synonym>SIJ strain - aftercare</Synonym>
		<Synonym>SIJ subluxation -aftercare</Synonym>
		<Synonym>SIJ syndrome - aftercare</Synonym>
	</Synonyms>
</FocusAnnotations>
<QAPairs>
	<QAPair pid="1">
			<Question qid="0003449-1" qtype="information">What is (are) Sacroiliac joint pain - aftercare ?</Question>
			<Answer></Answer>
	</QAPair>
	<QAPair pid="2">
			<Question qid="0003449-2" qtype="information">What is (are) Sacroiliac joint pain - aftercare ?</Question>
			<Answer></Answer>
	</QAPair>
	<QAPair pid="3">
			<Question qid="0003449-3" qtype="outlook">What is the outlook for Sacroiliac joint pain - aftercare ?</Question>
			<Answer></Answer>
	</QAPair>
	<QAPair pid="7">
			<Question qid="0003449-7" qtype="when to contact a medical professional">Do I need to see a doctor for Sacroiliac joint pain - aftercare ?</Question>
			<Answer></Answer>
	</QAPair>
</QAPairs>
</Document>
