<?xml version="1.0" encoding="UTF-8"?>
<Document id="0003845" source="ADAM" url="https://www.nlm.nih.gov/medlineplus/ency/patientinstructions/000255.htm">
 <!--Answers from the A.D.A.M. medical encyclopedia were removed to comply with the MedlinePlus copyright-->
<Focus>Taking warfarin (Coumadin, Jantoven) - what to ask your doctor</Focus>
<FocusAnnotations>
	<Category>Other</Category>
	<Synonyms>
		<Synonym>Warfarin - what to ask your doctor</Synonym>
		<Synonym>Coumadin - what to ask your doctor</Synonym>
		<Synonym>What to ask your doctor about taking warfarin (Coumadin)</Synonym>
		<Synonym>Jantoven - what to ask your doctor</Synonym>
		<Synonym>What to ask your doctor about taking warfarin (Jantoven)</Synonym>
	</Synonyms>
</FocusAnnotations>
<QAPairs>
	<QAPair pid="1">
			<Question qid="0003845-1" qtype="information">Do you have information about Taking warfarin (Coumadin, Jantoven) - what to ask your doctor</Question>
			<Answer></Answer>
	</QAPair>
</QAPairs>
</Document>
