<?xml version="1.0" encoding="UTF-8"?>
<Document id="0003323" source="ADAM" url="https://www.nlm.nih.gov/medlineplus/ency/article/000026.htm">
 <!--Answers from the A.D.A.M. medical encyclopedia were removed to comply with the MedlinePlus copyright-->
<Focus>Radiation sickness</Focus>
<FocusAnnotations>
	<Category>Disease</Category>
	<UMLS>
		<CUIs>
			<CUI>C0392615</CUI>
			<CUI>C1510432</CUI>
			<CUI>C0034535</CUI>
		</CUIs>
		<SemanticTypes>
			<SemanticType>T037</SemanticType>
			<SemanticType>T047</SemanticType>
		</SemanticTypes>
		<SemanticGroup>Disorders</SemanticGroup>
	</UMLS>
	<Synonyms>
		<Synonym>Radiation poisoning</Synonym>
		<Synonym>radiation injury</Synonym>
		<Synonym>rad poisoning</Synonym>
	</Synonyms>
</FocusAnnotations>
<QAPairs>
	<QAPair pid="1">
			<Question qid="0003323-1" qtype="information">What is (are) Radiation sickness ?</Question>
			<Answer></Answer>
	</QAPair>
	<QAPair pid="2">
			<Question qid="0003323-2" qtype="considerations">What to do for Radiation sickness ?</Question>
			<Answer></Answer>
	</QAPair>
	<QAPair pid="3">
			<Question qid="0003323-3" qtype="causes">What causes Radiation sickness ?</Question>
			<Answer></Answer>
	</QAPair>
	<QAPair pid="4">
			<Question qid="0003323-4" qtype="symptoms">What are the symptoms of Radiation sickness ?</Question>
			<Answer></Answer>
	</QAPair>
	<QAPair pid="5">
			<Question qid="0003323-5" qtype="considerations">What to do for Radiation sickness ?</Question>
			<Answer></Answer>
	</QAPair>
	<QAPair pid="6">
			<Question qid="0003323-6" qtype="considerations">What to do for Radiation sickness ?</Question>
			<Answer></Answer>
	</QAPair>
	<QAPair pid="7">
			<Question qid="0003323-7" qtype="prevention">How to prevent Radiation sickness ?</Question>
			<Answer></Answer>
	</QAPair>
</QAPairs>
</Document>
